apininjas/__init__.py
apininjas/abc.py
apininjas/client.py
apininjas/enums.py
apininjas/errors.py
apininjas/finance.py
apininjas/http.py
apininjas/utils.py
apininjas/types/__init__.py
apininjas/types/finance.py
apininjas.py-0.2.0.dist-info/LICENSE
apininjas.py-0.2.0.dist-info/METADATA
apininjas.py-0.2.0.dist-info/WHEEL
apininjas.py-0.2.0.dist-info/top_level.txt
apininjas.py-0.2.0.dist-info/RECORD
